odoo/addons/account_tax_unece/README.rst
odoo/addons/account_tax_unece/__init__.py
odoo/addons/account_tax_unece/__manifest__.py
odoo/addons/account_tax_unece/data/unece_date.xml
odoo/addons/account_tax_unece/data/unece_tax_categ.xml
odoo/addons/account_tax_unece/data/unece_tax_type.xml
odoo/addons/account_tax_unece/i18n/account_tax_unece.pot
odoo/addons/account_tax_unece/models/__init__.py
odoo/addons/account_tax_unece/models/account_tax.py
odoo/addons/account_tax_unece/models/account_tax_template.py
odoo/addons/account_tax_unece/models/unece_code_list.py
odoo/addons/account_tax_unece/readme/CONFIGURE.rst
odoo/addons/account_tax_unece/readme/CONTRIBUTORS.rst
odoo/addons/account_tax_unece/readme/DESCRIPTION.rst
odoo/addons/account_tax_unece/static/description/icon.png
odoo/addons/account_tax_unece/static/description/index.html
odoo/addons/account_tax_unece/tests/__init__.py
odoo/addons/account_tax_unece/tests/test_account_invoice.py
odoo/addons/account_tax_unece/views/account_tax.xml
odoo/addons/account_tax_unece/views/account_tax_template.xml
odoo13_addon_account_tax_unece-13.0.1.0.1.dist-info/METADATA
odoo13_addon_account_tax_unece-13.0.1.0.1.dist-info/WHEEL
odoo13_addon_account_tax_unece-13.0.1.0.1.dist-info/top_level.txt
odoo13_addon_account_tax_unece-13.0.1.0.1.dist-info/RECORD
